snipsfakeweather/Snipsspec
snipsfakeweather/__init__.py
snipsfakeweather/snipsfakeweather.py
snipsfakeweather-1.1.1.2.dist-info/DESCRIPTION.rst
snipsfakeweather-1.1.1.2.dist-info/METADATA
snipsfakeweather-1.1.1.2.dist-info/RECORD
snipsfakeweather-1.1.1.2.dist-info/WHEEL
snipsfakeweather-1.1.1.2.dist-info/metadata.json
snipsfakeweather-1.1.1.2.dist-info/top_level.txt
