Metadata-Version: 2.0
Name: snipsfakeweather
Version: 1.1.1.2
Summary: Fake weather forescasts skill for Snips
Home-page: https://github.com/snipsco/snips-skill-fakeweather
Author: Michael Fester
Author-email: michael.fester@gmail.com
License: MIT
Keywords: snips
Platform: UNKNOWN
